pipforester/__init__.py
pipforester/deptree.py
pipforester-1.0.1.dist-info/LICENSE.md
pipforester-1.0.1.dist-info/METADATA
pipforester-1.0.1.dist-info/WHEEL
pipforester-1.0.1.dist-info/entry_points.txt
pipforester-1.0.1.dist-info/top_level.txt
pipforester-1.0.1.dist-info/RECORD
