Metadata-Version: 2.1
Name: pipforester
Version: 1.0.1
Summary: A tool to analyze the dependency graph of a pip package.
Author-email: Jens Klein et al <jk@kleinundpartner.at>
License: BSD 2-Clause License
Project-URL: Homepage, https://github.com/collective/pipforester
Project-URL: Bug Reports, https://github.com/collective/pipforester/issues
Project-URL: Source, https://github.com/collective/pipforester/
Keywords: pip,graph,analysis
Classifier: Development Status :: 5 - Production/Stable
Classifier: Intended Audience :: Developers
Classifier: Topic :: Software Development :: Build Tools
Classifier: License :: OSI Approved :: BSD License
Classifier: Operating System :: OS Independent
Classifier: Programming Language :: Python
Classifier: Programming Language :: Python :: 3.7
Classifier: Programming Language :: Python :: 3.8
Classifier: Programming Language :: Python :: 3.9
Classifier: Programming Language :: Python :: 3.10
Classifier: Programming Language :: Python :: 3.11
Requires-Python: >=3.7
License-File: LICENSE.md
Requires-Dist: click
Requires-Dist: networkx
Requires-Dist: pipdeptree
Requires-Dist: pygraphviz
Provides-Extra: test
Requires-Dist: pytest ; extra == 'test'
